LydiaMFcalc/Calc.py
LydiaMFcalc/__init__.py
lydiamfcalc-0.0.3.dist-info/LICENSE
lydiamfcalc-0.0.3.dist-info/WHEEL
lydiamfcalc-0.0.3.dist-info/METADATA
lydiamfcalc-0.0.3.dist-info/RECORD
