Metadata-Version: 2.1
Name: LydiaMFcalc
Version: 0.0.3
Summary: initialize LydiaMFcalc package 
Author-email: LyMoFi <l.moser-fischer@outlook.de>
Classifier: License :: OSI Approved :: MIT License
